INSPIRE_MEDS/__init__.py
INSPIRE_MEDS/__main__.py
INSPIRE_MEDS/commands.py
INSPIRE_MEDS/dataset.yaml
INSPIRE_MEDS/download.py
INSPIRE_MEDS/pre_MEDS.py
INSPIRE_MEDS/configs/ETL.yaml
INSPIRE_MEDS/configs/__init__.py
INSPIRE_MEDS/configs/event_configs.yaml
INSPIRE_MEDS/configs/main.yaml
INSPIRE_MEDS/configs/pre_MEDS.yaml
INSPIRE_MEDS/configs/runner.yaml
INSPIRE_MEDS/configs/table_preprocessors.yaml
inspire_meds-0.0.12.dist-info/licenses/LICENSE
inspire_meds-0.0.12.dist-info/METADATA
inspire_meds-0.0.12.dist-info/WHEEL
inspire_meds-0.0.12.dist-info/entry_points.txt
inspire_meds-0.0.12.dist-info/top_level.txt
inspire_meds-0.0.12.dist-info/RECORD
