Metadata-Version: 2.4
Name: INSPIRE-MEDS
Version: 0.0.12
Summary: An ETL pipeline to extract INSPIRE data into the MEDS format.
Author-email: Robin van de Water <robin.vandewater@hpi.de>, Matthew McDermott <mattmcdermott8@gmail.com>
Project-URL: Homepage, https://github.com/rvandewater/INSPIRE_MEDS_Template
Project-URL: Issues, https://github.com/rvandewater/INSPIRE_MEDS_Template/issues
Classifier: Programming Language :: Python :: 3
Classifier: License :: OSI Approved :: MIT License
Classifier: Operating System :: OS Independent
Requires-Python: >=3.11
License-File: LICENSE
Requires-Dist: meds-transforms~=0.2.4
Requires-Dist: requests
Requires-Dist: beautifulsoup4
Requires-Dist: hydra-core
Provides-Extra: dev
Requires-Dist: pre-commit<4; extra == "dev"
Provides-Extra: tests
Requires-Dist: pytest; extra == "tests"
Requires-Dist: pytest-cov; extra == "tests"
Requires-Dist: rootutils; extra == "tests"
Requires-Dist: hydra-joblib-launcher; extra == "tests"
Provides-Extra: local-parallelism
Requires-Dist: hydra-joblib-launcher; extra == "local-parallelism"
Provides-Extra: slurm-parallelism
Requires-Dist: hydra-submitit-launcher; extra == "slurm-parallelism"
Provides-Extra: docs
Requires-Dist: mkdocs==1.6.0; extra == "docs"
Requires-Dist: mkdocs-material==9.5.31; extra == "docs"
Requires-Dist: mkdocstrings[python,shell]==0.25.2; extra == "docs"
Requires-Dist: mkdocs-gen-files==0.5.0; extra == "docs"
Requires-Dist: mkdocs-literate-nav==0.6.1; extra == "docs"
Requires-Dist: mkdocs-section-index==0.3.9; extra == "docs"
Requires-Dist: mkdocs-git-authors-plugin==0.9.0; extra == "docs"
Requires-Dist: mkdocs-git-revision-date-localized-plugin==1.2.6; extra == "docs"
Dynamic: license-file
